radnn/__init__.py
radnn/core.py
radnn/errors.py
radnn/ml_system.py
radnn/utils.py
radnn/benchmark/__init__.py
radnn/benchmark/latency.py
radnn/data/__init__.py
radnn/data/dataset_base.py
radnn/data/dataset_base_legacy.py
radnn/data/errors.py
radnn/data/sample_preprocessor.py
radnn/data/sample_set.py
radnn/data/sample_set_kind.py
radnn/data/sequence_dataset.py
radnn/data/structs/__init__.py
radnn/data/structs/tree.py
radnn/data_beta/__init__.py
radnn/data_beta/data_feed.py
radnn/data_beta/dataset_base.py
radnn/data_beta/dataset_folder.py
radnn/data_beta/image_dataset.py
radnn/data_beta/image_dataset_files.py
radnn/data_beta/sample_set.py
radnn/data_beta/sequence_dataset.py
radnn/data_beta/subset_type.py
radnn/data_beta/tf_classification_data_feed.py
radnn/data_beta/preprocess/__init__.py
radnn/data_beta/preprocess/normalizer.py
radnn/data_beta/preprocess/standardizer.py
radnn/data_beta/structures/__init__.py
radnn/data_beta/structures/dictionary.py
radnn/evaluation/__init__.py
radnn/evaluation/evaluate_classification.py
radnn/experiment/__init__.py
radnn/experiment/identification.py
radnn/experiment/ml_experiment.py
radnn/experiment/ml_experiment_config.py
radnn/experiment/ml_experiment_env.py
radnn/experiment/ml_experiment_log.py
radnn/experiment/ml_experiment_store.py
radnn/images/__init__.py
radnn/images/colors.py
radnn/images/image_processor.py
radnn/learn/__init__.py
radnn/learn/keras/__init__.py
radnn/learn/keras/keras_best_state_saver.py
radnn/learn/keras/keras_learning_algorithm.py
radnn/learn/keras/keras_learning_rate_scheduler.py
radnn/learn/keras/keras_optimization_combo.py
radnn/learn/torch/__init__.py
radnn/learn/torch/ml_model_freezer.py
radnn/learn/torch/ml_trainer.py
radnn/learn/torch/staircase_lr_scheduler.py
radnn/models/__init__.py
radnn/models/model_factory.py
radnn/models/model_hyperparams.py
radnn/models/model_info.py
radnn/models/cnn/__init__.py
radnn/models/cnn/cnn_stem_setup.py
radnn/plots/__init__.py
radnn/plots/plot_auto_multi_image.py
radnn-0.1.1.dist-info/licenses/LICENSE.txt
radnn-0.1.1.dist-info/METADATA
radnn-0.1.1.dist-info/WHEEL
radnn-0.1.1.dist-info/top_level.txt
radnn-0.1.1.dist-info/RECORD
